[
  {
    "Id": "1",
    "Name": "Obafemi Awolowo University",
    "Acronym": "OAU",
    "SchoolCategoryId": "3"
  },
  {
    "Id": "2",
    "Name": "University of Lagos",
    "Acronym": "Unilag",
    "SchoolCategoryId": "3"
  },
  {
    "Id": "3",
    "Name": "University of Ibadan",
    "Acronym": "UI",
    "SchoolCategoryId": "3"
  },
  {
    "Id": "4",
    "Name": "Ambrose Alli University",
    "Acronym": "AAU",
    "SchoolCategoryId": "3"
  },
  {
    "Id": "5",
    "Name": "Olabisi Onabanjo University",
    "Acronym": "OOU",
    "SchoolCategoryId": "3"
  },
  {
    "Id": "6",
    "Name": "Lagos State Polytechnic",
    "Acronym": "Laspotech",
    "SchoolCategoryId": "2"
  },
  {
    "Id": "7",
    "Name": "Federal Polytechnic",
    "Acronym": "Yabatech",
    "SchoolCategoryId": "2"
  },
  {
    "Id": "8",
    "Name": "The Polytechnic Ibadan",
    "Acronym": "IbadanPoly",
    "SchoolCategoryId": "2"
  },
  {
    "Id": "9",
    "Name": "Moshood Abiola Polytechnic",
    "Acronym": "Mapoly",
    "SchoolCategoryId": "2"
  },
  {
    "Id": "10",
    "Name": "The Polytechnic, Calabar",
    "Acronym": "PolyCal",
    "SchoolCategoryId": "2"
  },
  {
    "Id": "11",
    "Name": "Adeniran Ogunsanya College",
    "Acronym": "AOC",
    "SchoolCategoryId": "1"
  }
]